{"setting":"{\"code\":\"let delta = [0]\\nlet valueColumn = $data.columns['value']\\nlet sum = 0;\\nfor(let i=1;i<valueColumn.length;i++) {\\n  sum += valueColumn[i]\\n  delta[i] = valueColumn[0] - sum\\n}\\nconsole.log(delta)\\n\\nreturn {\\n    title: {\\n        text: '深圳月最低生活费组成（单位:元）',\\n        subtext: 'From ExcelHome',\\n        sublink: 'http://e.weibo.com/1341556070/AjQH99che'\\n    },\\n    tooltip: {\\n        trigger: 'axis',\\n        axisPointer: {            // 坐标轴指示器，坐标轴触发有效\\n            type: 'shadow'        // 默认为直线，可选为：'line' | 'shadow'\\n        },\\n        formatter: function (params) {\\n            var tar = params[1];\\n            return tar.name + '<br/>' + tar.seriesName + ' : ' + tar.value;\\n        }\\n    },\\n    grid: {\\n        left: '3%',\\n        right: '4%',\\n        bottom: '3%',\\n        containLabel: true\\n    },\\n    xAxis: {\\n        type: 'category',\\n        splitLine: {show: false},\\n        data: $data.columns['fee']\\n    },\\n    yAxis: {\\n        type: 'value'\\n    },\\n    series: [\\n        {\\n            name: '辅助',\\n            type: 'bar',\\n            stack: '总量',\\n            itemStyle: {\\n                barBorderColor: 'rgba(0,0,0,0)',\\n                color: 'rgba(0,0,0,0)'\\n            },\\n            emphasis: {\\n                itemStyle: {\\n                    barBorderColor: 'rgba(0,0,0,0)',\\n                    color: 'rgba(0,0,0,0)'\\n                }\\n            },\\n            data: delta\\n        },\\n        {\\n            name: '生活费',\\n            type: 'bar',\\n            stack: '总量',\\n            label: {\\n                show: true,\\n                position: 'inside'\\n            },\\n            data: $data.columns['value']\\n        }\\n    ]\\n};\"}","type":"c-customize","parameters":"[]","dsName":"direct","dsType":"direct","parameterExts":{},"projection":"[{\"name\":\"fee\",\"index\":0,\"type\":\"text\",\"format\":\"\"},{\"name\":\"value\",\"index\":1,\"type\":\"number\",\"format\":\"\"}]","query":"{\n\t\"columns\": [\n\t\t\"fee\",\n\t\t\"value\"\n\t],\n\t\"rows\": [\n\t\t[\n\t\t\t\"总费用\",\n\t\t\t\"2900\"\n\t\t],\n\t\t[\n\t\t\t\"房租\",\n\t\t\t\"1200\"\n\t\t],\n\t\t[\n\t\t\t\"水电费\",\n\t\t\t\"300\"\n\t\t],\n\t\t[\n\t\t\t\"交通费\",\n\t\t\t\"200\"\n\t\t],\n\t\t[\n\t\t\t\"伙食费\",\n\t\t\t\"900\"\n\t\t],\n\t\t[\n\t\t\t\"日用品数\",\n\t\t\t\"300\"\n\t\t]\n\t]\n}","name":"living fees"}